symreg/__init__.py
symreg/ga.py
symreg/nsgaii.py
symreg/regressor.py
symreg-0.0.5.dist-info/LICENSE
symreg-0.0.5.dist-info/METADATA
symreg-0.0.5.dist-info/WHEEL
symreg-0.0.5.dist-info/top_level.txt
symreg-0.0.5.dist-info/RECORD
