Metadata-Version: 2.1
Name: symreg
Version: 0.0.5
Summary: A Symbolic Regression engine
Home-page: https://github.com/danuker/symreg
Author: Dan Gheorghe Haiduc
Author-email: danuthaiduc@gmail.com.com
License: UNKNOWN
Platform: UNKNOWN
Classifier: Programming Language :: Python :: 3
Classifier: License :: OSI Approved :: MIT License
Classifier: Operating System :: OS Independent
Requires-Python: >=3.8
License-File: LICENSE
Requires-Dist: numpy
Requires-Dist: orderedset
